Metadata-Version: 2.1
Name: win-wildcard
Version: 0.5.0
Summary: Expand wildcards in shells of Windows using the dir or the Get-ChildItem command
Home-page: https://github.com/tos-kamiya/win_wildcard
Author: Toshihiro Kamiya
Author-email: kamiya@mbj.nifty.com
License: Public Domain
Platform: UNKNOWN
Classifier: Programming Language :: Python :: 3.8
Classifier: Programming Language :: Python :: 3.9
Classifier: Programming Language :: Python :: 3.10
Classifier: License :: Public Domain
Classifier: Operating System :: MacOS :: MacOS X
Classifier: Operating System :: POSIX :: Linux
Classifier: Operating System :: Microsoft :: Windows
Requires-Python: >=3.8
License-File: LICENSE
